version.py
spicextract/__init__.py
spicextract/main.py
spicextract/common/__init__.py
spicextract/common/args_parser.py
spicextract/common/proxmox_exporter.py
spicextract-0.1.0.dist-info/METADATA
spicextract-0.1.0.dist-info/WHEEL
spicextract-0.1.0.dist-info/entry_points.txt
spicextract-0.1.0.dist-info/top_level.txt
spicextract-0.1.0.dist-info/RECORD
