Metadata-Version: 2.1
Name: spicextract
Version: 0.1.0
Summary: Util for easy download SPICE file for Proxmox VMs
Home-page: https://github.com/lHumaNl/SpiceXtract
Author: lHumaNl
Author-email: fisher_sam@mail.ru
License: MIT
Keywords: spice proxmox vm downloader
Classifier: Development Status :: 3 - Alpha
Classifier: Intended Audience :: Developers
Classifier: Topic :: Multimedia :: Sound/Audio
Classifier: License :: OSI Approved :: MIT License
Classifier: Programming Language :: Python :: 3
Classifier: Programming Language :: Python :: 3.6
Requires-Dist: requests
Requires-Dist: urllib3
